basic_zoom/__init__.py
basic_zoom/base.py
basic_zoom/exceptions.py
basic_zoom/print.py
basic_zoom/s2s_auth.py
basic_zoom-0.0.12.dist-info/LICENSE
basic_zoom-0.0.12.dist-info/METADATA
basic_zoom-0.0.12.dist-info/WHEEL
basic_zoom-0.0.12.dist-info/top_level.txt
basic_zoom-0.0.12.dist-info/RECORD
