Metadata-Version: 2.1
Name: basic-zoom
Version: 0.0.12
Summary: REST api client for Zoom
Home-page: https://github.com/jsteinberg1/basic_zoom
Author: Justin Steinberg
Author-email: jsteinberg@gmail.com
Platform: any
Classifier: Programming Language :: Python :: 3
Classifier: License :: OSI Approved :: GNU General Public License v3 or later (GPLv3+)
Classifier: Operating System :: OS Independent
Classifier: Development Status :: 3 - Alpha
Requires-Python: >=3.8
License-File: LICENSE
Requires-Dist: requests
Requires-Dist: PyJWT
Requires-Dist: requests-oauthlib
Requires-Dist: rich
